rterm_src/__init__.py
rterm_src/common.py
rterm_src/config.py
rterm_src/feeds.json
rterm_src/get_rss.py
rterm_src/get_twitter.py
rterm_src/run.py
rtermsrc/__init__.py
rtermsrc/common.py
rtermsrc/config.py
rtermsrc/get_rss.py
rtermsrc/get_twitter.py
rtermsrc/run.py
src/__init__.py
src/common.py
src/config.py
src/get_rss.py
src/get_twitter.py
src/run.py
rterm-1.6.2.dist-info/LICENSE
rterm-1.6.2.dist-info/METADATA
rterm-1.6.2.dist-info/WHEEL
rterm-1.6.2.dist-info/entry_points.txt
rterm-1.6.2.dist-info/top_level.txt
rterm-1.6.2.dist-info/RECORD
