Metadata-Version: 2.1
Name: rterm
Version: 1.6.2
Summary: Twitter and RSS reader client for CLI
Home-page: https://github.com/rainygirl/rterm
Author: Lee JunHaeng
Author-email: rainygirl@gmail.com
License: MIT License
Keywords: twitter,RSS,CLI,command line,terminal
Classifier: Environment :: Console
Classifier: License :: OSI Approved :: MIT License
Classifier: Operating System :: OS Independent
Classifier: Programming Language :: Python :: 3.7
Requires-Python: >=3.7
License-File: LICENSE
Requires-Dist: Pillow (>=9.0.1)
Requires-Dist: asciimatics (>=1.11.0)
Requires-Dist: feedparser (>=5.2.1)
Requires-Dist: tweepy (==3.8.0)
Requires-Dist: wcwidth (>=0.1.8)
